rsrcfork/__init__.py
rsrcfork/__main__.py
rsrcfork/api.py
rsrcfork/py.typed
rsrcfork/compress/__init__.py
rsrcfork/compress/common.py
rsrcfork/compress/dcmp0.py
rsrcfork/compress/dcmp1.py
rsrcfork/compress/dcmp2.py
rsrcfork-1.8.0.dist-info/LICENSE
rsrcfork-1.8.0.dist-info/METADATA
rsrcfork-1.8.0.dist-info/WHEEL
rsrcfork-1.8.0.dist-info/entry_points.txt
rsrcfork-1.8.0.dist-info/top_level.txt
rsrcfork-1.8.0.dist-info/RECORD
