Metadata-Version: 2.1
Name: rsrcfork
Version: 1.8.0
Summary: A pure Python, cross-platform library/tool for reading Macintosh resource data, as stored in resource forks and ``.rsrc`` files
Home-page: https://github.com/dgelessus/python-rsrcfork
Author: dgelessus
License: MIT
Keywords: rsrc,fork,resource,manager,macintosh,mac,macos
Platform: UNKNOWN
Classifier: Development Status :: 4 - Beta
Classifier: Intended Audience :: Developers
Classifier: Topic :: Software Development :: Disassemblers
Classifier: Topic :: System
Classifier: Topic :: Utilities
Classifier: License :: OSI Approved :: MIT License
Classifier: Operating System :: MacOS :: MacOS 9
Classifier: Operating System :: MacOS :: MacOS X
Classifier: Operating System :: OS Independent
Classifier: Programming Language :: Python
Classifier: Programming Language :: Python :: 3
Classifier: Programming Language :: Python :: 3 :: Only
Classifier: Programming Language :: Python :: 3.6
Classifier: Programming Language :: Python :: 3.7
Classifier: Programming Language :: Python :: 3.8
Requires-Python: >=3.6
